MANIFEST.in
README.md
pyproject.toml
requirements.txt
setup.py
hstreamdb/__init__.py
hstreamdb/types.py
hstreamdb/utils.py
hstreamdb.egg-info/PKG-INFO
hstreamdb.egg-info/SOURCES.txt
hstreamdb.egg-info/dependency_links.txt
hstreamdb.egg-info/requires.txt
hstreamdb.egg-info/top_level.txt
hstreamdb/aio/__init__.py
hstreamdb/aio/client.py
hstreamdb/aio/consumer.py
hstreamdb/aio/producer.py