Metadata-Version: 2.1
Name: hstreamdb
Version: 0.2.0
Summary: Python client for HStreamDB
Home-page: https://github.com/hstreamdb/hstreamdb-py
Author: lambda
Author-email: lambda@emqx.io
License: UNKNOWN
Project-URL: Bug Tracker, https://github.com/hstreamdb/hstreamdb-py/issues
Platform: UNKNOWN
Classifier: Programming Language :: Python :: 3
Classifier: License :: OSI Approved :: MIT License
Classifier: Operating System :: OS Independent
Requires-Python: >=3.7
